cNumPKG/__init__.py
cNumPKG-0.0.0.dist-info/METADATA
cNumPKG-0.0.0.dist-info/WHEEL
cNumPKG-0.0.0.dist-info/top_level.txt
cNumPKG-0.0.0.dist-info/RECORD
