Metadata-Version: 2.1
Name: cNumPKG
Version: 0.0.0
Summary: coming soon - package from cNum AS
Author-email: developer <notinuse@developeratcnumas.com>
